fontconfig/__init__.py
fontconfig/fontconfig.abi3.so
fontconfig/fontconfig.c
fontconfig/fontconfig.pyi
fontconfig/py.typed
fontconfig_py.libs/libexpat-c040f8fd.so.1.11.1
fontconfig_py-1.0.1.dist-info/METADATA
fontconfig_py-1.0.1.dist-info/WHEEL
fontconfig_py-1.0.1.dist-info/top_level.txt
fontconfig_py-1.0.1.dist-info/RECORD
fontconfig_py-1.0.1.dist-info/licenses/LICENSE
fontconfig_py-1.0.1.dist-info/licenses/NOTICE
fontconfig_py-1.0.1.dist-info/sboms/auditwheel.cdx.json
