Metadata-Version: 2.4
Name: fontconfig-py
Version: 1.0.1
Summary: Python bindings to fontconfig
Author-email: "CyberAgent, Inc." <yamaguchi_kota@cyberagent.co.jp>
License-Expression: MIT AND FTL
Project-URL: Homepage, https://github.com/kyamagu/fontconfig-py
Project-URL: Documentation, https://fontconfig-py.readthedocs.io
Keywords: fontconfig,fonts,typography,freetype,font-matching
Classifier: Development Status :: 5 - Production/Stable
Classifier: Intended Audience :: Developers
Classifier: Topic :: Software Development :: Libraries :: Python Modules
Classifier: Topic :: Text Processing :: Fonts
Classifier: Topic :: Multimedia :: Graphics
Classifier: Programming Language :: Python :: 3
Classifier: Programming Language :: Python :: 3.10
Classifier: Programming Language :: Python :: 3.11
Classifier: Programming Language :: Python :: 3.12
Classifier: Programming Language :: Python :: 3.13
Classifier: Programming Language :: Python :: 3.14
Classifier: Programming Language :: Python :: Implementation :: CPython
Classifier: Operating System :: MacOS :: MacOS X
Classifier: Operating System :: POSIX :: Linux
Classifier: Programming Language :: Cython
Classifier: Typing :: Typed
Requires-Python: <4.0,>=3.10
License-File: LICENSE
License-File: NOTICE
Dynamic: license-file
